mega_utils/__init__.py
mega_utils/utils.py
mega_utils-1.4.0.dist-info/LICENSE
mega_utils-1.4.0.dist-info/METADATA
mega_utils-1.4.0.dist-info/WHEEL
mega_utils-1.4.0.dist-info/top_level.txt
mega_utils-1.4.0.dist-info/RECORD
