Metadata-Version: 2.1
Name: mega-utils
Version: 1.4.0
Summary: Utility functions for the Mega cloud storage service
Home-page: https://github.com/tomhosker/mega_utils
Author: Tom Hosker
Author-email: tomdothosker@gmail.com
License: MIT
Platform: UNKNOWN
License-File: LICENSE
Requires-Dist: hosker-utils
